pyhamsys/__init__.py
pyhamsys/pyhamsys.py
pyhamsys-0.89.dist-info/licenses/LICENSE
pyhamsys-0.89.dist-info/METADATA
pyhamsys-0.89.dist-info/WHEEL
pyhamsys-0.89.dist-info/top_level.txt
pyhamsys-0.89.dist-info/RECORD
