Metadata-Version: 2.4
Name: pyhamsys
Version: 0.89
Summary: Some tools for Hamiltonian systems
Author-email: Cristel Chandre <cristel.chandre@cnrs.fr>
Maintainer-email: Cristel Chandre <cristel.chandre@cnrs.fr>
License: BSD-2-Clause
Project-URL: Homepage, http://github.com/cchandre/pyhamsys
Project-URL: GitHub, http://github.com/cchandre/pyhamsys
Keywords: Hamiltonian,symplectic integrators,ODE solver
Classifier: Programming Language :: Python :: 3
Classifier: Intended Audience :: Education
Classifier: Intended Audience :: Science/Research
Classifier: Operating System :: OS Independent
Classifier: Topic :: Scientific/Engineering
Classifier: Topic :: Scientific/Engineering :: Mathematics
Classifier: Topic :: Scientific/Engineering :: Chemistry
Classifier: Topic :: Scientific/Engineering :: Physics
Classifier: Topic :: Scientific/Engineering :: Astronomy
Requires-Python: >=3.8
License-File: LICENSE
Requires-Dist: numpy
Requires-Dist: sympy
Requires-Dist: scipy
Requires-Dist: scikit-learn
Requires-Dist: matplotlib
Dynamic: license-file
